worchestic/group.py
worchestic/matrix.py
worchestic/signals.py
worchestic-0.2.6.dist-info/LICENSE
worchestic-0.2.6.dist-info/METADATA
worchestic-0.2.6.dist-info/WHEEL
worchestic-0.2.6.dist-info/top_level.txt
worchestic-0.2.6.dist-info/RECORD
