Metadata-Version: 2.1
Name: worchestic
Version: 0.2.6
Summary: A generic controller for a switch fabric
Author-email: Roger Gammans <rgammans@gammascience.co.uk>
License: GNU GENERAL PUBLIC LICENSE
Keywords: routing,switch,kvm,hardware
Classifier: Intended Audience :: Manufacturing
Classifier: Intended Audience :: Telecommunications Industry
Classifier: Intended Audience :: Other Audience
Classifier: License :: OSI Approved :: GNU General Public License v3 or later (GPLv3+)
Classifier: Programming Language :: Python :: 3
Classifier: Development Status :: 2 - Pre-Alpha
Classifier: Topic :: Other/Nonlisted Topic
License-File: LICENSE
Requires-Dist: atomicx
